flowerfield/__init__.py
flowerfield-0.8.0.dist-info/LICENSE
flowerfield-0.8.0.dist-info/METADATA
flowerfield-0.8.0.dist-info/WHEEL
flowerfield-0.8.0.dist-info/top_level.txt
flowerfield-0.8.0.dist-info/RECORD
