Metadata-Version: 2.1
Name: flowerfield
Version: 0.8.0
Summary: Tiny python module to automaticallymap dictionaries to python objects.
Home-page: https://github.com/cmd410/flowerfield
Author: Crystal Melting Dot
Author-email: stresspassing@gmail.com
License: UNKNOWN
Platform: UNKNOWN
Classifier: Programming Language :: Python :: 3
Classifier: License :: OSI Approved :: MIT License
Classifier: Operating System :: OS Independent
